LiteJsonDb/LiteJsonDb.py
LiteJsonDb/__init__.py
LiteJsonDb/handler/__init__.py
LiteJsonDb/handler/db_operations.py
LiteJsonDb/handler/encrypt.py
LiteJsonDb/handler/method.py
LiteJsonDb/modules/__init__.py
LiteJsonDb/modules/csv.py
LiteJsonDb/modules/search.py
LiteJsonDb/modules/tgbot.py
LiteJsonDb/utility/__init__.py
LiteJsonDb/utility/utils.py
LiteJsonDb-3.5.2.dist-info/METADATA
LiteJsonDb-3.5.2.dist-info/WHEEL
LiteJsonDb-3.5.2.dist-info/top_level.txt
LiteJsonDb-3.5.2.dist-info/RECORD
