Metadata-Version: 2.2
Name: LiteJsonDb
Version: 3.5.2
Summary: A lightweight JSON-based database system. It's designed for simplicity and ease of use.
Author-email: Coding Team <codingteamgroup@gmail.com>
Requires-Python: >=3.7
Requires-Dist: cryptography==44.0.0
